request_counter/__init__.py
request_counter/admin.py
request_counter/apps.py
request_counter/middlewares.py
request_counter/models.py
request_counter/tests.py
request_counter/urls.py
request_counter/views.py
request_counter/management/commands/__init__.py
request_counter/management/commands/store_api_count.py
request_counter/migrations/0001_initial.py
request_counter/migrations/__init__.py
request_counter-1.6.0.dist-info/METADATA
request_counter-1.6.0.dist-info/WHEEL
request_counter-1.6.0.dist-info/top_level.txt
request_counter-1.6.0.dist-info/RECORD
