Metadata-Version: 2.1
Name: request-counter
Version: 1.6.0
Summary: monitor api request count
Home-page: https://github.com/satenderbuddy/django-request-counter.git
Author-email: Satender Singh <saten070@gmail.com>
License: BSD-3-Clause
Requires-Python: >=3.6
Requires-Dist: Django
Requires-Dist: redis
